LICENSE
elefantolib/__init__.py
elefantolib/auth/__init__.py
elefantolib/auth/consumer.py
elefantolib/auth/user.py
elefantolib/constants.py
elefantolib/context/__init__.py
elefantolib/context/context_service.py
elefantolib/exceptions.py
elefantolib/http_client/__init__.py
elefantolib/http_client/httpx_client.py
elefantolib/logger_config.py
elefantolib/middleware.py
elefantolib/provider/__init__.py
elefantolib/provider/django_provider/__init__.py
elefantolib/provider/fastapi_provider/__init__.py
elefantolib/websocket_client/__init__.py
elefantolib/websocket_client/websocket_client.py
elefantolib-0.12.1.dist-info/WHEEL
elefantolib-0.12.1.dist-info/LICENSE
elefantolib-0.12.1.dist-info/METADATA
elefantolib-0.12.1.dist-info/RECORD
