Metadata-Version: 2.1
Name: elefantolib
Version: 0.12.1
Summary: Elefanto lib
Home-page: https://github.com/elefanto-organization/elefantolib
License: MIT
Author: Elefanto
Author-email: elefanto@gmail.com
Requires-Python: >=3.10,<4.0
Classifier: License :: OSI Approved :: MIT License
Classifier: Operating System :: OS Independent
Classifier: Programming Language :: Python :: 3
Classifier: Programming Language :: Python :: 3.10
Classifier: Programming Language :: Python :: 3.11
Classifier: Topic :: Software Development :: Documentation
Classifier: Topic :: Software Development :: Libraries :: Python Modules
Classifier: Topic :: Software Development :: Quality Assurance
Requires-Dist: exceptiongroup (>=1.1.1,<2.0.0)
Requires-Dist: httpx (>=0.24.1,<0.25.0)
Requires-Dist: pyjwt (>=2.7.0,<3.0.0)
Requires-Dist: pytest-env (>=0.8.1,<0.9.0)
Requires-Dist: websockets (>=11.0.3,<12.0.0)
Project-URL: Repository, https://github.com/elefanto-organization/elefantolib
